SuperDuperMetroid-2.3.3.dist-info/RECORD
SuperDuperMetroid-2.3.3.dist-info/entry_points.txt
SuperDuperMetroid-2.3.3.dist-info/METADATA
SuperDuperMetroid-2.3.3.dist-info/WHEEL
SuperDuperMetroid-2.3.3.dist-info/top_level.txt
SuperDuperMetroid-2.3.3.dist-info/LICENSE
SuperDuperMetroid/SM_Constants.py
SuperDuperMetroid/SM_Interface.py
SuperDuperMetroid/__init__.py
SuperDuperMetroid/VramItems.bin
SuperDuperMetroid/SM_Room_Header_Data.py
SuperDuperMetroid/__main__.py
SuperDuperMetroid/ROM_Patcher.py
SuperDuperMetroid/IPS_Patcher.py
SuperDuperMetroid/BPSPatch/__init__.py
SuperDuperMetroid/BPSPatch/BPS_Patcher.cpython-38-x86_64-linux-gnu.so
SuperDuperMetroid/Patches/Mandatory Patches/varia_timer_fix.ips
SuperDuperMetroid/Patches/Mandatory Patches/door_transition.ips
SuperDuperMetroid/Patches/Mandatory Patches/varia_rng.ips
SuperDuperMetroid/Patches/Mandatory Patches/seed_display.ips
SuperDuperMetroid/Patches/Animals/ridleyimals.ips
SuperDuperMetroid/Patches/Animals/no_animals.ips
SuperDuperMetroid/Patches/Animals/metalimals.ips
SuperDuperMetroid/Patches/Animals/escapimals.ips
SuperDuperMetroid/Patches/Animals/grey_door_animals.ips
SuperDuperMetroid/Patches/Animals/phantoonimals.ips
SuperDuperMetroid/Patches/Animals/low_timer.ips
SuperDuperMetroid/Patches/Animals/animals.ips
SuperDuperMetroid/Patches/Animals/animal_enemies.ips
SuperDuperMetroid/Patches/Animals/draygonimals.ips
SuperDuperMetroid/Patches/Music/no_music.ips
SuperDuperMetroid/Patches/Music/custom_music.ips
SuperDuperMetroid/Patches/Music/random_music.ips
SuperDuperMetroid/Patches/Fixes/fix_spacetime_beam.ips
SuperDuperMetroid/Patches/Fixes/fix_screw_attack_menu.ips
SuperDuperMetroid/Patches/Fixes/fix_heat_echoes.ips
SuperDuperMetroid/Patches/Fixes/disable_gt_code.ips
SuperDuperMetroid/Patches/Accessibility/colorblind.ips
SuperDuperMetroid/Patches/Map Changes/red_tower.ips
SuperDuperMetroid/Patches/Map Changes/dachora_pit.ips
SuperDuperMetroid/Patches/Map Changes/nova_boost_platform.ips
SuperDuperMetroid/Patches/Map Changes/moat.ips
SuperDuperMetroid/Patches/Map Changes/early_super_bridge.ips
SuperDuperMetroid/Patches/Map Changes/pre_high_jump.ips
SuperDuperMetroid/Patches/Map Changes/pre_spazer.ips
