Metadata-Version: 2.1
Name: SuperDuperMetroid
Version: 2.3.3
Summary: A Super Metroid patching utility
Home-page: https://github.com/SolventMercury/Super-Duper-Metroid
Author: Samuel Roy
Project-URL: Bug Tracker, https://github.com/SolventMercury/super-Duper-Metroid/issues
Classifier: Programming Language :: Python :: 3
Classifier: License :: OSI Approved :: MIT License
Classifier: Operating System :: OS Independent
Requires-Python: >=3.8
License-File: LICENSE
